{
  "cli": {
    "version": ">= 14.5.0",
    "appVersionSource": "remote"
  },
  "build": {
    "development": {
      "developmentClient": true,
      "distribution": "internal",
      "ios": {
        "simulator": false
      }
    },
    "preview": {
      "distribution": "internal",
      "ios": {
        "simulator": false
      }
    },
    "production": {
      "autoIncrement": true,
      "ios": {
        "simulator": false
      },
      "android": {
        "gradleCommand": ":app:assembleRelease"
      }
    }
  },
  "submit": {
    "production": {
      "ios": {
        "appleId": "caroline.chan0923@gmail.com",
        "ascAppId": "6741072637"
      }
    }
  }
}